{"stats":{"minecraft:mined":{"minecraft:seagrass":4,"minecraft:tall_seagrass":2},"minecraft:custom":{"minecraft:jump":30,"minecraft:time_since_rest":15278,"minecraft:damage_taken":20,"minecraft:crouch_one_cm":675,"minecraft:leave_game":3,"minecraft:play_time":15278,"minecraft:walk_on_water_one_cm":5266,"minecraft:time_since_death":15278,"minecraft:walk_one_cm":4494,"minecraft:sneak_time":440,"minecraft:total_world_time":15278,"minecraft:walk_under_water_one_cm":6168,"minecraft:swim_one_cm":2662,"minecraft:fall_one_cm":880,"minecraft:fly_one_cm":26}},"DataVersion":3465}